Workbook

Sheet Evaluation_Summary
A1: Vendor Name | B1: Category | C1: Overall Score | D1: Recommendation | E1: Decision Date | F1: Owner
A2: Vendor A — VoiceCare AI | B2: AI Voice Agent — Behavioral Health | C2: =IF(SUM(Criteria_Scoring!C:C)=0,"",SUM(Criteria_Scoring!E:E)/SUM(Criteria_Scoring!C:C)*100) | D2: Conditional | E2: 2026-04-29 | F2: Product Lead
A4: Scoring Breakdown
A5: Total Criteria: | B5: =COUNTA(Criteria_Scoring!A:A)-1
A6: Criteria Scored 4+: | B6: =COUNTIF(Criteria_Scoring!D:D,">="&4)
A7: Criteria Scored <=2: | B7: =COUNTIF(Criteria_Scoring!D:D,"<="&2)
A8: Clinical Safety Items Met: | B8: =COUNTIF(Clinical_Safety!D:D,"Yes")
A9: HIPAA Items Compliant: | B9: =COUNTIF(HIPAA_Compliance!C:C,"Compliant")
A10: Contract Terms Acceptable: | B10: =COUNTIF(Contract_Requirements!D:D,"Yes")

Sheet Criteria_Scoring
A1: Criterion | B1: Category | C1: Weight (%) | D1: Score (1-5) | E1: Weighted Score | F1: Evidence/Notes
A2: Crisis detection accuracy (suicidal ideation, self-harm) | B2: Clinical Safety | C2: 15 | D2: 4 | E2: =C2*D2/100 | F2: Vendor claims 94% sensitivity on internal benchmark; independent validation pending
A3: Clinical scope guardrails (no diagnosis, no prescribing) | B3: Clinical Safety | C3: 10 | D3: 3 | E3: =C3*D3/100 | F3: Guardrails present but triggered inconsistently on edge-case prompts during demo
A4: De-escalation protocol adherence | B4: Clinical Safety | C4: 10 | D4: 4 | E4: =C4*D4/100 | F4: Follows motivational interviewing framework; warm handoff to crisis line confirmed
A5: BAA execution and terms | B5: HIPAA & Compliance | C5: 8 | D5: 5 | E5: =C5*D5/100 | F5: Standard BAA signed; includes breach notification within 24 hours
A6: 42 CFR Part 2 compliance (SUD data) | B6: HIPAA & Compliance | C6: 8 | D6: 3 | E6: =C6*D6/100 | F6: Vendor unfamiliar with Part 2 requirements; needs custom consent flow for SUD data
A7: SOC 2 Type II certification | B7: HIPAA & Compliance | C7: 5 | D7: 4 | E7: =C7*D7/100 | F7: SOC 2 Type II report dated 2025-09; annual audit cycle confirmed
A8: athenahealth EHR integration (FHIR R4) | B8: Integration | C8: 8 | D8: 3 | E8: =C8*D8/100 | F8: FHIR R4 API available; athenahealth-specific connector in beta, not GA
A9: Salesforce Health Cloud integration | B9: Integration | C9: 5 | D9: 4 | E9: =C9*D9/100 | F9: Native Salesforce app available; supports custom object mapping
A10: Telephony platform compatibility (Twilio / RingCentral) | B10: Integration | C10: 5 | D10: 5 | E10: =C10*D10/100 | F10: Twilio SIP trunk verified; RingCentral integration via partner
A11: Per-call cost vs. current cost-per-touchpoint | B11: Cost & Value | C11: 5 | D11: 3 | E11: =C11*D11/100 | F11: $1.20/call vs. $4.80 current staff cost; volume discounts above 10K calls/month
A12: Implementation cost and timeline | B12: Cost & Value | C12: 3 | D12: 3 | E12: =C12*D12/100 | F12: $85K implementation; 12-week timeline including EHR integration
A13: Total cost of ownership (3-year projection) | B13: Cost & Value | C13: 4 | D13: 3 | E13: =C13*D13/100 | F13: 3-year TCO ~$420K including licensing, integration, and support
... A17: Voice naturalness and latency | B17: User Experience | C17: 3 | D17: 4 | E17: =C17*D17/100 | F17: Sub-500ms response latency; voice quality rated 'natural' by 78% of test users
B18: TOTAL | C18: =SUM(C2:C17) | E18: =SUM(E2:E17)

Sheet Clinical_Safety
A1: Requirement ID | B1: Requirement | C1: Priority | D1: Met? | E1: Evidence | F1: Gap Notes
A2: CS-001 | B2: System must detect crisis language (suicidal ideation, self-harm, overdose intent) and immediately route to crisis line | C2: Must | D2: Partial | E2: Demo showed detection of explicit statements; missed indirect/coded language in 2 of 8 test cases | F2: Require additional testing with behavioral health-specific crisis lexicon
A3: CS-002 | B3: System must not provide clinical diagnoses, medication recommendations, or treatment plans | C3: Must | D3: Yes | E3: Tested 25 prompts attempting to elicit clinical advice; all correctly deflected
A4: CS-003 | B4: System must implement warm handoff to live clinician within 30 seconds when requested | C4: Must | D4: Yes | E4: Average handoff time 18 seconds in demo; queue management configurable
A5: CS-004 | B5: System must de-escalate distressed callers using trauma-informed language | C5: Must | D5: Partial | E5: Motivational interviewing framework present; trauma-informed care vocabulary needs customization | F5: Need to train on Eleanor Health's clinical communication guidelines
A6: CS-005 | B6: System must log all interactions for clinical quality review | C6: Must | D6: Yes | E6: Full transcript and audio recording with configurable retention; HIPAA-compliant storage
A7: CS-006 | B7: System must not continue conversation if patient reports active medical emergency | C7: Must | D7: Yes | E7: Emergency detection triggers 911 routing script; tested with 5 emergency scenarios
A8: CS-007 | B8: System must respect patient opt-out and Do Not Call preferences | C8: Should | D8: Yes | E8: Opt-out recorded in real time; syncs to DNC list within 1 hour
A9: CS-008 | B9: System must identify and appropriately handle minors (under 18) | C9: Should | D9: No | E9: No age verification or minor-specific workflow exists | F9: Need custom workflow for minor callers; consider parental consent requirements
A10: CS-009 | B10: System must detect substance use crisis indicators (overdose symptoms, withdrawal distress) | C10: Must | D10: Partial | E10: General crisis detection present; SUD-specific indicators not in training data | F10: Vendor to add SUD crisis lexicon; validate with Eleanor clinical team
A11: CS-010 | B11: System must not store or repeat back sensitive disclosures (assault, abuse) beyond the session | C11: Must | D11: Yes | E11: Session memory is ephemeral; sensitive topics flagged but not persisted in patient profile

Sheet HIPAA_Compliance
A1: Requirement ID | B1: Requirement | C1: Status | D1: Evidence | E1: Risk if Unmet
A2: HC-001 | B2: Execute Business Associate Agreement (BAA) covering all PHI handling | C2: Compliant | D2: BAA signed 2026-03-15; covers voice data, transcripts, and metadata | E2: HIPAA violation; potential OCR enforcement action and fines up to $1.5M per category
A3: HC-002 | B3: Encrypt PHI at rest (AES-256) and in transit (TLS 1.2+) | C3: Compliant | D3: AES-256 at rest confirmed; TLS 1.3 in transit; encryption keys managed via AWS KMS | E3: Data breach exposure; HIPAA Security Rule violation
A4: HC-003 | B4: Maintain audit logs of all PHI access for minimum 6 years | C4: Compliant | D4: CloudTrail + application-level audit logs; 7-year retention configured | E4: Cannot demonstrate compliance during audit; HIPAA Administrative Safeguard violation
A5: HC-004 | B5: 42 CFR Part 2 compliant consent management for SUD treatment data | C5: Non-Compliant | D5: Vendor does not currently support Part 2 consent workflows | E5: Federal violation for unauthorized SUD data disclosure; criminal penalties possible
A6: HC-005 | B6: Breach notification within 72 hours per HIPAA Breach Notification Rule | C6: Compliant | D6: BAA specifies 24-hour vendor notification to covered entity; incident response plan reviewed | E6: Delayed breach response; regulatory penalties and patient harm
A7: HC-006 | B7: Role-based access control (RBAC) for all PHI systems | C7: Compliant | D7: RBAC implemented with quarterly access reviews; MFA required for all admin access | E7: Unauthorized PHI access; minimum necessary standard violation
A8: HC-007 | B8: Data residency within United States (no offshore processing) | C8: Compliant | D8: All processing in AWS us-east-1 and us-west-2; no cross-border data transfer | E8: Potential state privacy law violations; patient trust concerns
A9: HC-008 | B9: Patient right to access and delete voice recordings | C9: Partial | D9: Access request workflow exists; deletion workflow in development (ETA Q2 2026) | E9: HIPAA Right of Access violation; OCR enforcement priority area
A10: HC-009 | B10: Annual HIPAA security risk assessment | C10: Compliant | D10: Most recent risk assessment dated 2025-11; third-party assessor (Coalfire) | E10: Non-compliance with HIPAA Security Rule; audit finding
A11: HC-010 | B11: Workforce training on PHI handling and security awareness | C11: Compliant | D11: Annual training with 98% completion rate; phishing simulation program active | E11: Human error leading to breach; HIPAA Administrative Safeguard gap
A12: HC-011 | B12: De-identification of data used for model training (Safe Harbor or Expert Determination) | C12: Partial | D12: Safe Harbor method applied to training data; re-identification risk assessment not completed | E12: Using PHI for model training without authorization; HIPAA Privacy Rule violation
A13: HC-012 | B13: Subcontractor/sub-processor BAAs for all downstream vendors | C13: Compliant | D13: Sub-processor list provided; BAAs in place for AWS, Twilio, and transcription service | E13: Downstream breach without contractual protection; liability exposure

Sheet Integration_Assessment
A1: System | B1: Integration Type | C1: Feasibility | D1: Effort Estimate | E1: Dependencies | F1: Notes
A2: athenahealth EHR | B2: FHIR R4 API (Patient, Encounter, DocumentReference) | C2: Medium | D2: 6-8 weeks | E2: athenahealth Marketplace approval; FHIR R4 sandbox access | F2: athenahealth connector in beta; may need custom adapter for Eleanor's workflow
A3: Salesforce Health Cloud | B3: REST API + Custom Objects (Care Plan, Task) | C3: High | D3: 3-4 weeks | E3: Salesforce Connected App setup; Eleanor custom object schema | F3: Native Salesforce app available; bi-directional sync for care coordination tasks
A4: Twilio Telephony | B4: SIP Trunk + Programmable Voice API | C4: High | D4: 1-2 weeks | E4: Twilio account configuration; SIP trunk provisioning | F4: Vendor has production Twilio integration; supports call recording and real-time transcription
A5: Data Warehouse (Snowflake) | B5: Batch ETL via S3 + Snowpipe | C5: High | D5: 2-3 weeks | E5: Snowflake staging schema; IAM role for S3 access | F5: Vendor exports call metadata and outcomes in Parquet format; daily batch load
A6: Ops Platform (internal scheduling) | B6: REST API webhook for appointment reminders | C6: Medium | D6: 4-5 weeks | E6: Internal API documentation; webhook endpoint security review | F6: Custom integration required; vendor has webhook framework but needs Eleanor-specific payload mapping

Sheet Pilot_Design
A1: Metric | B1: Baseline | C1: Target | D1: Measurement Method | E1: Duration | F1: Success Threshold | G1: Owner
A2: Appointment show rate | B2: 62% | C2: 72% | D2: athenahealth appointment status report (kept vs. no-show) | E2: 90 days | F2: >= 70% show rate in pilot cohort | G2: Director of Operations
A3: Patient engagement rate (calls answered/completed) | B3: 35% (current outbound answer rate) | C3: 55% | D3: Twilio call disposition logs + vendor dashboard | E3: 90 days | F3: >= 50% engagement rate | G3: Product Lead
A4: Crisis detection accuracy | B4: N/A (new capability) | C4: 95% sensitivity | D4: Clinical review of flagged vs. unflagged calls (random sample n=200) | E4: 90 days | F4: >= 90% sensitivity; zero missed critical events | G4: Chief Clinical Officer
A5: Patient satisfaction (post-call survey) | B5: 3.8/5.0 (current IVR satisfaction) | C5: 4.3/5.0 | D5: Post-call SMS survey (1-5 scale); minimum 30% response rate | E5: 90 days | F5: >= 4.0/5.0 with >= 30% response rate | G5: Patient Experience Manager
A6: Cost per successful patient touchpoint | B6: $4.80/touchpoint (staff outreach) | C6: $2.00/touchpoint | D6: Total vendor cost / completed calls resulting in action (appointment, refill, etc.) | E6: 90 days | F6: <= $2.50/touchpoint | G6: Finance Lead
A7: Clinical escalation appropriateness | B7: N/A (new capability) | C7: >= 90% appropriate escalations | D7: Clinical team review of all escalated calls; rate as appropriate/inappropriate | E7: 90 days | F7: >= 85% appropriate; zero missed escalations | G7: Clinical Quality Manager
A8: Staff time recaptured (hours/week) | B8: 0 hours (current state) | C8: 40 hours/week across pilot sites | D8: Time study: staff hours on outbound calls pre/post pilot | E8: 90 days | F8: >= 30 hours/week recaptured | G8: Director of Operations
A9: System uptime and reliability | B9: N/A | C9: 99.9% uptime | D9: Vendor SLA dashboard + internal monitoring (PagerDuty) | E9: 90 days | F9: >= 99.5% uptime; zero unplanned outages > 30 min | G9: Engineering Lead

Sheet Contract_Requirements
A1: Term | B1: Requirement | C1: Vendor Response | D1: Acceptable? | E1: Negotiation Notes
A2: Business Associate Agreement | B2: Fully executed BAA covering voice data, transcripts, metadata, and derived analytics | C2: Standard BAA provided; covers all PHI categories | D2: Yes
A3: Data ownership and portability | B3: Eleanor Health retains ownership of all patient data; vendor provides data export within 30 days of termination | C3: Data ownership clause included; export in Parquet + JSON format | D3: Yes
A4: Model training data usage | B4: Vendor may NOT use Eleanor patient data to train models for other customers without explicit written consent | C4: Agreed to opt-out; default is opt-in for aggregate model improvement | D4: No | E4: Require explicit opt-out as DEFAULT, not opt-in. Non-negotiable for Part 2 compliance.
A5: SLA: uptime guarantee | B5: 99.9% uptime SLA with service credits for breach | C5: 99.5% standard SLA; 99.9% available on Enterprise tier at +15% cost | D5: No | E5: Negotiate 99.9% into base contract; clinical use case requires higher reliability
A6: Termination and wind-down | B6: 90-day termination for convenience with 180-day wind-down support | C6: 60-day termination; 90-day wind-down | D6: Yes | E6: Acceptable; shorter than requested but operationally feasible
A7: Liability cap | B7: Liability cap of 2x annual contract value; unlimited for data breach and willful misconduct | C7: 1x annual contract value; unlimited for data breach only | D7: No | E7: Push for 2x cap; add willful misconduct carve-out
A8: Insurance requirements | B8: Vendor carries $5M cyber liability insurance and $2M professional liability (E&O) | C8: $5M cyber; $1M E&O | D8: No | E8: Require $2M E&O minimum given clinical use case; verify certificate of insurance
A9: Security incident response | B9: Vendor notifies Eleanor within 24 hours of any security incident; provides root cause analysis within 5 business days | C9: 24-hour notification agreed; RCA within 10 business days | D9: Yes | E9: 10-day RCA acceptable; add requirement for interim status updates every 48 hours
A10: Audit rights | B10: Eleanor Health may audit vendor security controls annually; vendor provides SOC 2 Type II report | C10: SOC 2 Type II provided annually; on-site audit with 30-day notice | D10: Yes
A11: Regulatory change management | B11: Vendor adapts to regulatory changes (HIPAA, state privacy laws, 42 CFR Part 2) within 90 days of effective date | C11: Best-effort compliance; no SLA on regulatory adaptation | D11: No | E11: Require contractual SLA for regulatory compliance updates; critical for behavioral health
